 [
     {
         "id": "5edecef9b440f930b0d67c15",
         "balance": "$1,306.82",
         "picture": "http://placehold.it/32x32",
         "age": 36,
         "eyeColor": "green",
         "name": "Mostafizur Rahman",
         "gender": "male",
         "company": "FLEETMIX",
         "email": "mostafiz@fleetmix.com",
         "phone": "+1 (977) 522-2940",
         "website": "https://www.json-generator.com"
     },
     {
         "id": "5edecef9b440f930b0d67c15",
         "balance": "$1,306.82",
         "picture": "http://placehold.it/32x32",
         "age": 36,
         "eyeColor": "green",
         "name": "Glass Hartman",
         "gender": "male",
         "company": "FLEETMIX",
         "email": "glasshartman@fleetmix.com",
         "phone": "+1 (977) 522-2940",
         "website": "https://www.json-generator.com"
     },
     {
         "id": "5edecef9b440f930b0d67c15",
         "balance": "$1,306.82",
         "picture": "http://placehold.it/32x32",
         "age": 36,
         "eyeColor": "green",
         "name": "Farzana",
         "gender": "Fmale",
         "company": "FLEETMIX",
         "email": "farzana@fleetmix.com",
         "phone": "+1 (977) 522-2940",
         "website": "http://flutter-util.glitch.me"
     },
     {
         "id": "5edecef9b440f930b0d67c15",
         "balance": "$1,306.82",
         "picture": "http://placehold.it/32x32",
         "age": 36,
         "eyeColor": "green",
         "name": "Monoyara Momo",
         "gender": "fmale",
         "company": "FLEETMIX",
         "email": "monoyara@fleetmix.com",
         "phone": "+1 (977) 522-2940",
         "website": "https://www.json-generator.com"
     },
     {
     "id": "5edecef9b440f930b0d67c15",
     "balance": "$1,306.82",
     "picture": "http://placehold.it/32x32",
     "age": 36,
     "eyeColor": "green",
     "name": "Mir Minhan",
     "gender": "male",
     "company": "FLEETMIX",
     "email": "minhan@fleetmix.com",
     "phone": "+1 (977) 522-2940",
     "website": "https://www.json-generator.com"
 },
     {
         "id": "5edecef9b440f930b0d67c15",
         "balance": "$1,306.82",
         "picture": "http://placehold.it/32x32",
         "age": 36,
         "eyeColor": "green",
         "name": "Sofiqul Islam",
         "gender": "male",
         "company": "FLEETMIX",
         "email": "sofiqul@fleetmix.com",
         "phone": "+1 (977) 522-2940",
         "website": "https://www.json-generator.com"
     },
     {
     "id": "5edecef9b440f930b0d67c15",
     "balance": "$1,306.82",
     "picture": "http://placehold.it/32x32",
     "age": 36,
     "eyeColor": "green",
     "name": "Mahabub Rahman",
     "gender": "male",
     "company": "FLEETMIX",
     "email": "mahabub@fleetmix.com",
     "phone": "+1 (977) 522-2940",
     "website": "https://www.json-generator.com"
 },
     {
         "id": "5edecef9b440f930b0d67c15",
         "balance": "$1,306.82",
         "picture": "http://placehold.it/32x32",
         "age": 36,
         "eyeColor": "green",
         "name": "Swapon Khan",
         "gender": "male",
         "company": "FLEETMIX",
         "email": "swapon@fleetmix.com",
         "phone": "+1 (977) 522-2940",
         "website": "https://www.json-generator.com"
     },
     {
         "id": "5edecef9b440f930b0d67c15",
         "balance": "$1,306.82",
         "picture": "http://placehold.it/32x32",
         "age": 36,
         "eyeColor": "green",
         "name": "Prity",
         "gender": "male",
         "company": "FLEETMIX",
         "email": "prity@fleetmix.com",
         "phone": "+1 (977) 522-2940",
         "website": "https://www.json-generator.com"
     },
     {
         "id": "5edecef9b440f930b0d67c15",
         "balance": "$1,306.82",
         "picture": "http://placehold.it/32x32",
         "age": 36,
         "eyeColor": "green",
         "name": "Halim Monddol",
         "gender": "male",
         "company": "FLEETMIX",
         "email": "halim@fleetmix.com",
         "phone": "+1 (977) 522-2940",
         "website": "https://www.json-generator.com"
     }
  ]